gana/__init__.py
gana/block/__init__.py
gana/block/program.py
gana/block/solution.py
gana/operators/__init__.py
gana/operators/composition.py
gana/operators/convolution.py
gana/operators/sigma.py
gana/sets/__init__.py
gana/sets/birth.py
gana/sets/cases.py
gana/sets/constraint.py
gana/sets/function.py
gana/sets/index.py
gana/sets/objective.py
gana/sets/parameter.py
gana/sets/theta.py
gana/sets/variable.py
gana/shapes/__init__.py
gana/shapes/box.py
gana/shapes/edge.py
gana/shapes/facet.py
gana/shapes/vertex.py
gana/utils/__init__.py
gana/utils/decorators.py
gana/utils/draw.py
gana/utils/printing.py
gana/value/__init__.py
gana/value/bigm.py
gana/value/zero.py
gana-1.0.9.dist-info/licenses/LICENSE
gana-1.0.9.dist-info/METADATA
gana-1.0.9.dist-info/WHEEL
gana-1.0.9.dist-info/top_level.txt
gana-1.0.9.dist-info/RECORD
