Metadata-Version: 2.4
Name: gana
Version: 1.0.9
Summary: A barebones mathematical programming package
Author-email: Rahul Kakodkar <cacodcar@gmail.com>
Maintainer-email: Rahul Kakodkar <cacodcar@gmail.com>
License: MIT License
Project-URL: Homepage, https://github.com/cacodcar/gana
Project-URL: Issues, https://github.com/cacodcar/gana/issues
Keywords: modeling,optimization,programming,aml
Classifier: Programming Language :: Python :: 3.13
Classifier: Programming Language :: Python :: 3.12
Classifier: License :: OSI Approved :: MIT License
Classifier: Operating System :: OS Independent
Requires-Python: >=3.12
License-File: LICENSE
Requires-Dist: ppopt
Requires-Dist: gurobipy
Requires-Dist: IPython
Requires-Dist: numpy
Requires-Dist: pandas
Requires-Dist: matplotlib
Provides-Extra: all
Requires-Dist: pyomo; extra == "all"
Requires-Dist: sympy; extra == "all"
Provides-Extra: test
Requires-Dist: coverage; extra == "test"
Requires-Dist: pytest; extra == "test"
Requires-Dist: hypothesis; extra == "test"
Requires-Dist: flake8; extra == "test"
Provides-Extra: docs
Requires-Dist: sphinx; extra == "docs"
Requires-Dist: sphinx-book-theme; extra == "docs"
Requires-Dist: nbsphinx; extra == "docs"
Requires-Dist: sphinx_mdinclude; extra == "docs"
Requires-Dist: myst-nb; extra == "docs"
Requires-Dist: sphinxcontrib-bibtex; extra == "docs"
Requires-Dist: sphinx-copybutton; extra == "docs"
Requires-Dist: sphinx-togglebutton; extra == "docs"
Requires-Dist: sphinx-thebe; extra == "docs"
Requires-Dist: sphinx-design; extra == "docs"
Requires-Dist: sphinx-examples; extra == "docs"
Requires-Dist: sphinx-tabs; extra == "docs"
Requires-Dist: sphinxext-opengraph; extra == "docs"
Dynamic: license-file
